start_md_project/__init__.py
start_md_project-0.1.0.dist-info/licenses/LICENSE.txt
start_md_project-0.1.0.dist-info/METADATA
start_md_project-0.1.0.dist-info/WHEEL
start_md_project-0.1.0.dist-info/entry_points.txt
start_md_project-0.1.0.dist-info/top_level.txt
start_md_project-0.1.0.dist-info/RECORD
